<!DOCTYPE suite SYSTEM "https://testng.org/testng-1.0.dtd" >
<suite name="Smoke Test Suite">

    <test name="Test group 1">


        <classes>

            <class name="tests2.BasicParametrization">
                <parameter name="usr" value="Hello"></parameter>
                <parameter name="pass" value="world"></parameter>

                <methods>
                    <include name="testUsername"/>
                </methods>
            </class>

        </classes>

    </test>

    <test name="Test group 2">


        <classes>

            <class name="tests2.BasicParametrization">
                <parameter name="usr" value="Tester"></parameter>
                <parameter name="pass" value="test"></parameter>

                <methods>
                    <include name="testUsername"/>
                </methods>
            </class>

        </classes>

    </test>








    <!--    <test name="API tests">-->

<!--    </test>-->



</suite>